{
    "firstName": "Mirian",
    "lastName": "Revishvili",
    "userImage1": "https://raw.githubusercontent.com/Ninochakvetadze/img/6893d5df4a2b5e0b8b7bb817c4af0519a210247a/userimage1.svg",
    "userImage": "https://raw.githubusercontent.com/Ninochakvetadze/img/main/Profile.jpg",
    "age": "24",
    "address": "Tbilisi, Georgia",
    "job": "Front-End",
    "residence": "BD",
    "freelance": "Avialable",
    "social": [{ "title": "facebook", "url": "https://www.facebook.com/" }],
    "myServices": "Amet minim mollit non deserunt ullamco est sit aliqua dolor do amet sint. Velit officia consequat duis enim velit mollit. lorem ipsum",
    "languages": [
        {
            "language": "English",
            "level": 80
        },
        {
            "language": "Spanish",
            "level": 60
        }
    ],
    "skills": [
        {
            "language": "HTML",
            "level": 80
        },
        {
            "language": "CSS",
            "level": 60
        },
        {
            "language": "Js",
            "level": 30
        }
    ],
    "extraSkills": [
        {
            "icon": "Bootstrap, Materialize"
        },
        {
            "icon": "Stylus, Sass, Less"
        },
        {
            "icon": "Gulp, Webpack, Grunt"
        },
        {
            "icon": "GIT Knowledge"
        }
    ],
    "services": [
        {
            "title": "Web Development",
            "description": "Blog, E-Comerce"
        },
        {
            "title": "UI/UX Design",
            "description": "Mobile Website Design"
        },
        {
            "title": "Sound Design",
            "description": "Voice Over, Beat Making"
        },
        {
            "title": "Game Design",
            "description": "Character Design, Props & Objects"
        },
        {
            "title": "Photography",
            "description": "Portrait, Product Photography"
        },
        {
            "title": "Advertising",
            "desscription": "Lorem ipsum dolor sit amet, consectetur adipiscing elit. Vitae nulla diam in ac dictum a urna viverra morbi."
        }
    ]
}
